{"nodes": [{"id": "c_users_inkno_documents_github_cheque_extractor_frontend_app_public_terms_page_tsx", "label": "page.tsx", "file_type": "code", "source_file": "C:\\Users\\inkno\\Documents\\GitHub\\cheque-extractor\\frontend\\app\\(public)\\terms\\page.tsx", "source_location": "L1"}, {"id": "terms_page_termsofservicepage", "label": "TermsOfServicePage()", "file_type": "code", "source_file": "C:\\Users\\inkno\\Documents\\GitHub\\cheque-extractor\\frontend\\app\\(public)\\terms\\page.tsx", "source_location": "L9"}], "edges": [{"source": "c_users_inkno_documents_github_cheque_extractor_frontend_app_public_terms_page_tsx", "target": "link", "relation": "imports_from", "context": "import", "confidence": "EXTRACTED", "source_file": "C:\\Users\\inkno\\Documents\\GitHub\\cheque-extractor\\frontend\\app\\(public)\\terms\\page.tsx", "source_location": "L1", "weight": 1.0}, {"source": "c_users_inkno_documents_github_cheque_extractor_frontend_app_public_terms_page_tsx", "target": "lucide_react", "relation": "imports_from", "context": "import", "confidence": "EXTRACTED", "source_file": "C:\\Users\\inkno\\Documents\\GitHub\\cheque-extractor\\frontend\\app\\(public)\\terms\\page.tsx", "source_location": "L2", "weight": 1.0}, {"source": "c_users_inkno_documents_github_cheque_extractor_frontend_app_public_terms_page_tsx", "target": "terms_page_termsofservicepage", "relation": "contains", "confidence": "EXTRACTED", "source_file": "C:\\Users\\inkno\\Documents\\GitHub\\cheque-extractor\\frontend\\app\\(public)\\terms\\page.tsx", "source_location": "L9", "weight": 1.0}], "raw_calls": [{"caller_nid": "terms_page_termsofservicepage", "callee": "recognition", "is_member_call": false, "source_file": "C:\\Users\\inkno\\Documents\\GitHub\\cheque-extractor\\frontend\\app\\(public)\\terms\\page.tsx", "source_location": "L38"}, {"caller_nid": "terms_page_termsofservicepage", "callee": "transactions", "is_member_call": false, "source_file": "C:\\Users\\inkno\\Documents\\GitHub\\cheque-extractor\\frontend\\app\\(public)\\terms\\page.tsx", "source_location": "L38"}, {"caller_nid": "terms_page_termsofservicepage", "callee": "plans", "is_member_call": false, "source_file": "C:\\Users\\inkno\\Documents\\GitHub\\cheque-extractor\\frontend\\app\\(public)\\terms\\page.tsx", "source_location": "L55"}, {"caller_nid": "terms_page_termsofservicepage", "callee": "accuracy", "is_member_call": false, "source_file": "C:\\Users\\inkno\\Documents\\GitHub\\cheque-extractor\\frontend\\app\\(public)\\terms\\page.tsx", "source_location": "L82"}]}